base_django_rest_framework/__init__.py
base_django_rest_framework/admin/__init__.py
base_django_rest_framework/admin/oauth2/__init__.py
base_django_rest_framework/admin/oauth2/client.py
base_django_rest_framework/admin/user.py
base_django_rest_framework/apps/__init__.py
base_django_rest_framework/authentication/__init__.py
base_django_rest_framework/authentication/oauth2.py
base_django_rest_framework/conf/__init__.py
base_django_rest_framework/fixtures/oauth2/client.json
base_django_rest_framework/fixtures/oauth2/token.json
base_django_rest_framework/fixtures/user.json
base_django_rest_framework/management/__init__.py
base_django_rest_framework/management/commands/__init__.py
base_django_rest_framework/management/commands/create_oauth2_client.py
base_django_rest_framework/management/commands/delete_expired_oauth2_tokens.py
base_django_rest_framework/management/commands/delete_revoked_oauth2_tokens.py
base_django_rest_framework/managers/__init__.py
base_django_rest_framework/managers/oauth2/__init__.py
base_django_rest_framework/managers/oauth2/client.py
base_django_rest_framework/managers/oauth2/token.py
base_django_rest_framework/managers/user.py
base_django_rest_framework/migrations/0001_initial.py
base_django_rest_framework/migrations/__init__.py
base_django_rest_framework/models/__init__.py
base_django_rest_framework/models/mixins.py
base_django_rest_framework/models/oauth2/__init__.py
base_django_rest_framework/models/oauth2/client.py
base_django_rest_framework/models/oauth2/token.py
base_django_rest_framework/models/user.py
base_django_rest_framework/oauth2/__init__.py
base_django_rest_framework/oauth2/endpoints/__init__.py
base_django_rest_framework/oauth2/endpoints/revocation.py
base_django_rest_framework/oauth2/grants/__init__.py
base_django_rest_framework/oauth2/grants/password.py
base_django_rest_framework/oauth2/grants/refresh.py
base_django_rest_framework/permissions/__init__.py
base_django_rest_framework/permissions/model.py
base_django_rest_framework-1.0.0.dist-info/COPYING
base_django_rest_framework-1.0.0.dist-info/METADATA
base_django_rest_framework-1.0.0.dist-info/WHEEL
base_django_rest_framework-1.0.0.dist-info/RECORD
