Metadata-Version: 2.1
Name: base-django-rest-framework
Version: 1.0.0
Summary: Base Django Rest Framework Project Setup
Home-page: https://github.com/evnskc/base-django-rest-framework
License: GPL-3.0-or-later
Keywords: base,django,django rest framework
Author: Evans
Author-email: evans@fundi.dev
Requires-Python: >=3.11,<4.0
Classifier: License :: OSI Approved :: GNU General Public License v3 or later (GPLv3+)
Classifier: Programming Language :: Python :: 3
Classifier: Programming Language :: Python :: 3.11
Requires-Dist: authlib (>=1.2.1,<2.0.0)
Requires-Dist: django (>=4.2.3,<5.0.0)
Requires-Dist: djangorestframework (>=3.14.0,<4.0.0)
Requires-Dist: hiredis (>=2.2.3,<3.0.0)
Requires-Dist: pillow (>=10.0.0,<11.0.0)
Requires-Dist: psycopg (>=3.1.9,<4.0.0)
Requires-Dist: redis (>=4.6.0,<5.0.0)
Requires-Dist: sentry-sdk[django] (>=1.27.0,<2.0.0)
Project-URL: Documentation, https://github.com/evnskc/base-django-rest-framework
Project-URL: Repository, https://github.com/evnskc/base-django-rest-framework
